filerobot/__init__.py
filerobot-0.0.25.dist-info/LICENSE
filerobot-0.0.25.dist-info/METADATA
filerobot-0.0.25.dist-info/WHEEL
filerobot-0.0.25.dist-info/top_level.txt
filerobot-0.0.25.dist-info/RECORD
