Metadata-Version: 2.1
Name: filerobot
Version: 0.0.25
Summary: A filerobot library which interacts with filerobot API
Author: Scaleflex
Requires-Python: >=3.6
License-File: LICENSE
